{
  "name": "Люблю с комочками!",
  "icon": "pyrotech:rock:11",
  "category": "gather_material",
  "pages": [
    {
      "type": "spotlight",
      "link_recipe": true,
      "item": "pyrotech:rock:11",
      "text": "Маленькие $(item)комочки$() можно отыскать, если порыться в грязи. А можно просто создать их на верстаке."
    },
    {
      "type": "crafting",
      "recipe": "pyrotech:mud"
    },
    {
      "type": "rt_soaking_pot_recipe",
      "recipe": "pyrotech:mud_clump"
    },
    {
      "type": "relations",
      "entries": [
        "gather/mud"
      ]
    }
  ]
}